teleapp/__init__.py
teleapp/teleapp.py
teleapp/cmd/__init__.py
teleapp/cmd/cmd.cpython-36m-aarch64-linux-gnu.so
teleapp/const/__init__.py
teleapp/const/click_setting.cpython-36m-aarch64-linux-gnu.so
teleapp-0.3.0.dist-info/METADATA
teleapp-0.3.0.dist-info/WHEEL
teleapp-0.3.0.dist-info/entry_points.txt
teleapp-0.3.0.dist-info/top_level.txt
teleapp-0.3.0.dist-info/RECORD
