Metadata-Version: 2.1
Name: teleapp
Version: 0.3.0
Summary: Command line toolkit for tele app
Home-page: UNKNOWN
Author: imason
Author-email: moy7@chinatelecom.cn
License: UNKNOWN
Keywords: teleapp
Platform: UNKNOWN
Classifier: Programming Language :: Python :: 3
Classifier: License :: OSI Approved :: MIT License
Classifier: Operating System :: OS Independent
Requires-Python: >=3.6,
Requires-Dist: pytelerdac (==0.4.0)
